README.md
setup.py
curses_snake/__init__.py
curses_snake/cli.py
curses_snake.egg-info/PKG-INFO
curses_snake.egg-info/SOURCES.txt
curses_snake.egg-info/dependency_links.txt
curses_snake.egg-info/entry_points.txt
curses_snake.egg-info/not-zip-safe
curses_snake.egg-info/requires.txt
curses_snake.egg-info/top_level.txt