Metadata-Version: 2.1
Name: curses-snake
Version: 1.0.3
Summary: Snake game in console based on cureses.
Home-page: https://github.com/VoIlAlex/curses-snake
Author: voilalex
Author-email: ilya.vouk@gmail.com
License: MIT
Download-URL: https://github.com/VoIlAlex/curses-snake/archive/v1.0.3.tar.gz
Keywords: game,console,curses,snake
Platform: UNKNOWN
Classifier: Development Status :: 5 - Production/Stable
Classifier: Environment :: Console :: Curses
Classifier: Topic :: Games/Entertainment
Classifier: Programming Language :: Python :: 3.5
Classifier: Programming Language :: Python :: 3.6
Classifier: Programming Language :: Python :: 3.7
Classifier: Programming Language :: Python :: 3.8
